Workbook

Sheet Справочник слов
A1: Слово | B1: Перевод | C1: Тип | D1: Сложность | E1: Тема
A2: kerb | B2: бордюр,ограничение | C2: существительное | D2: C2
A3: follower | B3: последователь | C3: существительное | D3: C2
A4: dim | B4: тусклый,слабый | C4: прилагательное | D4: C2
A5: hollow | B5: глухой (звук) | C5: прилагательное | D5: C2
A6: instinct | B6: инстинкт | C6: существительное | D6: C2
A7: to dread | B7: бояться,страшиться | C7: глагол | D7: C2
A8: conviction | B8: убеждение,признание виновным | C8: существительное | D8: C2
A9: to rot | B9: гнить | C9: глагол | D9: C2
A10: mercy | B10: пощада,милосердие | C10: существительное | D10: C2 | E10: Характер человека
A11: to giggle | B11: хихикать | C11: глагол | D11: C2 | E11: Действия человека
A12: to bind | B12: связывать,привязывать | C12: глагол | D12: C2
A13: to plead | B13: умолять,вымаливать | C13: глагол | D13: C2 | E13: Общение
A14: to retrieve | B14: извлекать,доставать | C14: глагол | D14: C2 | E14: Действия человека
A15: prime | B15: основной,главный | C15: прилагательное | D15: C2
A16: ritual | B16: ритуал,обряд | C16: существительное | D16: C2
A17: to suppress | B17: подавлять,сдерживать | C17: глагол | D17: C2
A18: resistance | B18: сопротивление,сопротивляемость | C18: существительное | D18: C2 | E18: Тело и здоровье
A19: intent | B19: намерение,умысел | C19: существительное | D19: C2
A20: civilian | B20: гражданское лицо,штатский | C20: существительное | D20: C2
A21: subtle | B21: тонкий,неуловимый | C21: прилагательное | D21: C2
A22: raid | B22: рейд,набег | C22: существительное | D22: C2
A23: knuckle | B23: костяшки пальцев | C23: существительное | D23: C2 | E23: Тело и здоровье
A24: wicked | B24: злой,безнравственный | C24: прилагательное | D24: C2 | E24: Характер человека
A25: scrap | B25: крохи,объедки | C25: существительное | D25: C2
A26: strand | B26: прядь,стренга | C26: существительное | D26: C2
A27: fireplace | B27: камин,очаг | C27: существительное | D27: C2
A28: to crumble | B28: крошить,крошиться | C28: глагол | D28: C2
A29: prey | B29: добыча,жертва | C29: существительное | D29: C2 | E29: Животные
A30: sorrow | B30: печаль,скорбь | C30: существительное | D30: C2 | E30: Характер человека
A31: heap | B31: куча,груда | C31: существительное | D31: C2
A32: globe | B32: глобус | C32: существительное | D32: C2
A33: pursuit | B33: погоня,преследование | C33: существительное | D33: C2
A34: wary | B34: осторожный,настороженный | C34: прилагательное | D34: C2 | E34: Характер человека
A35: to contemplate | B35: обдумывать,задумываться | C35: глагол | D35: C2
A36: strap | B36: ремешок,ремень | C36: существительное | D36: C2 | E36: Одежда
A37: lump | B37: комок | C37: существительное | D37: C2
A38: to yield | B38: уступать,производить | C38: глагол | D38: C2
A39: to loosen | B39: ослаблять | C39: глагол | D39: C2
A40: to flatten | B40: распластать,выравнивать | C40: глагол | D40: C2
A41: contempt | B41: презрение | C41: существительное | D41: C2 | E41: Характер человека
A42: to imply | B42: подразумевать,намекать | C42: глагол | D42: C2 | E42: Общение
A43: bundle | B43: пачка,пучок | C43: существительное | D43: C2
A44: to execute | B44: казнить,выполнять | C44: глагол | D44: C2
A45: grain | B45: зерно,крупица | C45: существительное | D45: C2 | E45: Еда и напитки
A46: residence | B46: резиденция,проживание | C46: существительное | D46: C2
A47: rigid | B47: жесткий,строгий | C47: прилагательное | D47: C2
A48: frantic | B48: полный отчаяния,лихорадочный,отчаянный | C48: прилагательное | D48: C2
A49: weed | B49: сорняк | C49: существительное | D49: C2 | E49: Природа
A50: intensity | B50: интенсивность | C50: существительное | D50: C2
A51: ribbon | B51: лента | C51: существительное | D51: C2
A52: disgust | B52: отвращение,омерзение | C52: существительное | D52: C2 | E52: Характер человека
A53: conscience | B53: совесть,сознание | C53: существительное | D53: C2
A54: to squeak | B54: скрипеть,пищать | C54: глагол | D54: C2
A55: counsel | B55: адвокат,совет | C55: существительное | D55: C2
A56: timber | B56: древесина,лесоматериалы | C56: существительное | D56: C2
A57: tender | B57: нежный,чувствительный | C57: прилагательное | D57: C2 | E57: Еда и напитки; Характер человека
A58: hostage | B58: заложник,залог | C58: существительное | D58: C2
A59: formation | B59: образование,формирование | C59: существительное | D59: C2
A60: dignity | B60: достоинство,сан | C60: существительное | D60: C2 | E60: Характер человека
A61: plague | B61: чума,бедствие | C61: существительное | D61: C2 | E61: Тело и здоровье
A62: threshold | B62: порог,предел | C62: существительное | D62: C2
A63: alliance | B63: союз,альянс | C63: существительное | D63: C2
A64: intruder | B64: незваный гость,злоумышленник | C64: существительное | D64: C2
A65: handy | B65: удобный,портативный | C65: прилагательное | D65: C2
A66: dismay | B66: смятение,страх | C66: существительное | D66: C2
A67: vicious | B67: злобный,порочный | C67: прилагательное | D67: C2
A68: transmission | B68: передача,коробка передач | C68: существительное | D68: C2 | E68: Искусство и медиа
A69: elaborate | B69: сложный,замысловатый | C69: прилагательное | D69: C2
A70: compliment | B70: комплимент | C70: существительное | D70: C2
A71: intact | B71: неповрежденный,нетронутый | C71: прилагательное | D71: C2
A72: to vomit | B72: вызывать рвоту,тошнить | C72: глагол | D72: C2 | E72: Тело и здоровье
A73: velvet | B73: бархат,бархатистость | C73: существительное | D73: C2 | E73: Одежда
A74: recognition | B74: признание,осознание | C74: существительное | D74: C2
A75: assembly | B75: собрание,сборка | C75: существительное | D75: C2
A76: likewise | B76: подобным образом,так же | C76: наречие | D76: C2
A77: to sustain | B77: поддерживать,понести | C77: глагол | D77: C2
A78: to strive | B78: стремиться,бороться | C78: глагол | D78: C2
A79: petty | B79: мелкий,мелочный | C79: прилагательное | D79: C2
A80: blunt | B80: тупой,туповатый | C80: прилагательное | D80: C2 | E80: Характер человека
A81: infant | B81: младенец | C81: существительное | D81: C2
A82: bleak | B82: мрачный,холодный | C82: прилагательное | D82: C2
A83: refuge | B83: убежище | C83: существительное | D83: C2
A84: fragile | B84: хрупкий,слабый | C84: прилагательное | D84: C2 | E84: Характер человека
A85: awe | B85: благоговение,трепет | C85: существительное | D85: C2
A86: to peek | B86: подглядывать | C86: глагол | D86: C2
A87: casualty | B87: несчастный случай,раненый | C87: существительное | D87: C2
A88: veteran | B88: ветеран,фронтовик | C88: существительное | D88: C2
A89: sane | B89: здравомыслящий,нормальный | C89: прилагательное | D89: C2 | E89: Тело и здоровье
A90: plump | B90: пухлый,полный | C90: прилагательное | D90: C2 | E90: Тело и здоровье
A91: virtue | B91: достоинство,добродетель | C91: существительное | D91: C2
A92: ignorant | B92: невежественный,несведущий | C92: прилагательное | D92: C2
A93: to arouse | B93: пробуждать,вызывать | C93: глагол | D93: C2
A94: naval | B94: морской,флотский | C94: прилагательное | D94: C2
A95: to testify | B95: давать показания,свидетельствовать | C95: глагол | D95: C2
A96: fraction | B96: фракция,дробь | C96: существительное | D96: C2
A97: fearful | B97: страшный,боящийся | C97: прилагательное | D97: C2 | E97: Характер человека
A98: goodness | B98: доброта,добродетель | C98: существительное | D98: C2
A99: wholly | B99: полностью,совершенно | C99: наречие | D99: C2
A100: sequence | B100: последовательность,ряд | C100: существительное | D100: C2
...

Sheet Аналитика
A1: Аналитика справочника
A3: Всего записей | B3: =COUNTA('Справочник слов'!A2:A1000) -> 13823
A4: Уникальных слов | B4: =IFERROR(__xludf.DUMMYFUNCTION("COUNTUNIQUE(ARRAYFORMULA(LOWER(FILTER('Справочник слов'!A2:A1000,'Справочник слов'!A2:A1000<>""""))))"),13533.0) -> 13533
A6: Уровень | B6: Количество слов | D6: Тип | E6: Количество слов | G6: Тема | H6: Количество слов
A7: A1 | B7: =COUNTIF('Справочник слов'!D2:D1000,A7) -> 752 | D7: артикль | E7: =COUNTIF('Справочник слов'!C2:C1000,D7)+COUNTIF('Справочник слов'!C2:C1000,D7&", *")+COUNTIF('Справочник слов'!C2:C1000,"*, "&D7)+COUNTIF('Справочник слов'!C2:C1000,"*, "&D7&", *") -> 3 | G7: Внешность человека | H7: =COUNTIF('Справочник слов'!E2:E1000,G7)+COUNTIF('Справочник слов'!E2:E1000,G7&"; *")+COUNTIF('Справочник слов'!E2:E1000,"*; "&G7)+COUNTIF('Справочник слов'!E2:E1000,"*; "&G7&"; *") -> 120
A8: A2 | B8: =COUNTIF('Справочник слов'!D2:D1000,A8) -> 1206 | D8: глагол | E8: =COUNTIF('Справочник слов'!C2:C1000,D8)+COUNTIF('Справочник слов'!C2:C1000,D8&", *")+COUNTIF('Справочник слов'!C2:C1000,"*, "&D8)+COUNTIF('Справочник слов'!C2:C1000,"*, "&D8&", *") -> 2523 | G8: Действия человека | H8: =COUNTIF('Справочник слов'!E2:E1000,G8)+COUNTIF('Справочник слов'!E2:E1000,G8&"; *")+COUNTIF('Справочник слов'!E2:E1000,"*; "&G8)+COUNTIF('Справочник слов'!E2:E1000,"*; "&G8&"; *") -> 976
A9: B1 | B9: =COUNTIF('Справочник слов'!D2:D1000,A9) -> 2854 | D9: глагольная фраза | E9: =COUNTIF('Справочник слов'!C2:C1000,D9)+COUNTIF('Справочник слов'!C2:C1000,D9&", *")+COUNTIF('Справочник слов'!C2:C1000,"*, "&D9)+COUNTIF('Справочник слов'!C2:C1000,"*, "&D9&", *") -> 17 | G9: Деньги | H9: =COUNTIF('Справочник слов'!E2:E1000,G9)+COUNTIF('Справочник слов'!E2:E1000,G9&"; *")+COUNTIF('Справочник слов'!E2:E1000,"*; "&G9)+COUNTIF('Справочник слов'!E2:E1000,"*; "&G9&"; *") -> 240
A10: B2 | B10: =COUNTIF('Справочник слов'!D2:D1000,A10) -> 3956 | D10: грамматическая конструкция | E10: =COUNTIF('Справочник слов'!C2:C1000,D10)+COUNTIF('Справочник слов'!C2:C1000,D10&", *")+COUNTIF('Справочник слов'!C2:C1000,"*, "&D10)+COUNTIF('Справочник слов'!C2:C1000,"*, "&D10&", *") -> 1 | G10: Еда и напитки | H10: =COUNTIF('Справочник слов'!E2:E1000,G10)+COUNTIF('Справочник слов'!E2:E1000,G10&"; *")+COUNTIF('Справочник слов'!E2:E1000,"*; "&G10)+COUNTIF('Справочник слов'!E2:E1000,"*; "&G10&"; *") -> 325
A11: C1 | B11: =COUNTIF('Справочник слов'!D2:D1000,A11) -> 3197 | D11: междометие | E11: =COUNTIF('Справочник слов'!C2:C1000,D11)+COUNTIF('Справочник слов'!C2:C1000,D11&", *")+COUNTIF('Справочник слов'!C2:C1000,"*, "&D11)+COUNTIF('Справочник слов'!C2:C1000,"*, "&D11&", *") -> 14 | G11: Животные | H11: =COUNTIF('Справочник слов'!E2:E1000,G11)+COUNTIF('Справочник слов'!E2:E1000,G11&"; *")+COUNTIF('Справочник слов'!E2:E1000,"*; "&G11)+COUNTIF('Справочник слов'!E2:E1000,"*; "&G11&"; *") -> 126
A12: C2 | B12: =COUNTIF('Справочник слов'!D2:D1000,A12) -> 1858 | D12: местоимение | E12: =COUNTIF('Справочник слов'!C2:C1000,D12)+COUNTIF('Справочник слов'!C2:C1000,D12&", *")+COUNTIF('Справочник слов'!C2:C1000,"*, "&D12)+COUNTIF('Справочник слов'!C2:C1000,"*, "&D12&", *") -> 79 | G12: Искусство и медиа | H12: =COUNTIF('Справочник слов'!E2:E1000,G12)+COUNTIF('Справочник слов'!E2:E1000,G12&"; *")+COUNTIF('Справочник слов'!E2:E1000,"*; "&G12)+COUNTIF('Справочник слов'!E2:E1000,"*; "&G12&"; *") -> 335
D13: модальный глагол | E13: =COUNTIF('Справочник слов'!C2:C1000,D13)+COUNTIF('Справочник слов'!C2:C1000,D13&", *")+COUNTIF('Справочник слов'!C2:C1000,"*, "&D13)+COUNTIF('Справочник слов'!C2:C1000,"*, "&D13&", *") -> 7 | G13: Образование | H13: =COUNTIF('Справочник слов'!E2:E1000,G13)+COUNTIF('Справочник слов'!E2:E1000,G13&"; *")+COUNTIF('Справочник слов'!E2:E1000,"*; "&G13)+COUNTIF('Справочник слов'!E2:E1000,"*; "&G13&"; *") -> 163
D14: наречие | E14: =COUNTIF('Справочник слов'!C2:C1000,D14)+COUNTIF('Справочник слов'!C2:C1000,D14&", *")+COUNTIF('Справочник слов'!C2:C1000,"*, "&D14)+COUNTIF('Справочник слов'!C2:C1000,"*, "&D14&", *") -> 1113 | G14: Общение | H14: =COUNTIF('Справочник слов'!E2:E1000,G14)+COUNTIF('Справочник слов'!E2:E1000,G14&"; *")+COUNTIF('Справочник слов'!E2:E1000,"*; "&G14)+COUNTIF('Справочник слов'!E2:E1000,"*; "&G14&"; *") -> 819
D15: определитель | E15: =COUNTIF('Справочник слов'!C2:C1000,D15)+COUNTIF('Справочник слов'!C2:C1000,D15&", *")+COUNTIF('Справочник слов'!C2:C1000,"*, "&D15)+COUNTIF('Справочник слов'!C2:C1000,"*, "&D15&", *") -> 45 | G15: Одежда | H15: =COUNTIF('Справочник слов'!E2:E1000,G15)+COUNTIF('Справочник слов'!E2:E1000,G15&"; *")+COUNTIF('Справочник слов'!E2:E1000,"*; "&G15)+COUNTIF('Справочник слов'!E2:E1000,"*; "&G15&"; *") -> 132
D16: предлог | E16: =COUNTIF('Справочник слов'!C2:C1000,D16)+COUNTIF('Справочник слов'!C2:C1000,D16&", *")+COUNTIF('Справочник слов'!C2:C1000,"*, "&D16)+COUNTIF('Справочник слов'!C2:C1000,"*, "&D16&", *") -> 135 | G16: Отношения | H16: =COUNTIF('Справочник слов'!E2:E1000,G16)+COUNTIF('Справочник слов'!E2:E1000,G16&"; *")+COUNTIF('Справочник слов'!E2:E1000,"*; "&G16)+COUNTIF('Справочник слов'!E2:E1000,"*; "&G16&"; *") -> 180
D17: прилагательное | E17: =COUNTIF('Справочник слов'!C2:C1000,D17)+COUNTIF('Справочник слов'!C2:C1000,D17&", *")+COUNTIF('Справочник слов'!C2:C1000,"*, "&D17)+COUNTIF('Справочник слов'!C2:C1000,"*, "&D17&", *") -> 2636 | G17: Покупки | H17: =COUNTIF('Справочник слов'!E2:E1000,G17)+COUNTIF('Справочник слов'!E2:E1000,G17&"; *")+COUNTIF('Справочник слов'!E2:E1000,"*; "&G17)+COUNTIF('Справочник слов'!E2:E1000,"*; "&G17&"; *") -> 366
D18: приставка | E18: =COUNTIF('Справочник слов'!C2:C1000,D18)+COUNTIF('Справочник слов'!C2:C1000,D18&", *")+COUNTIF('Справочник слов'!C2:C1000,"*, "&D18)+COUNTIF('Справочник слов'!C2:C1000,"*, "&D18&", *") -> 3 | G18: Политика | H18: =COUNTIF('Справочник слов'!E2:E1000,G18)+COUNTIF('Справочник слов'!E2:E1000,G18&"; *")+COUNTIF('Справочник слов'!E2:E1000,"*; "&G18)+COUNTIF('Справочник слов'!E2:E1000,"*; "&G18&"; *") -> 104
D19: словосочетание | E19: =COUNTIF('Справочник слов'!C2:C1000,D19)+COUNTIF('Справочник слов'!C2:C1000,D19&", *")+COUNTIF('Справочник слов'!C2:C1000,"*, "&D19)+COUNTIF('Справочник слов'!C2:C1000,"*, "&D19&", *") -> 13 | G19: Природа | H19: =COUNTIF('Справочник слов'!E2:E1000,G19)+COUNTIF('Справочник слов'!E2:E1000,G19&"; *")+COUNTIF('Справочник слов'!E2:E1000,"*; "&G19)+COUNTIF('Справочник слов'!E2:E1000,"*; "&G19&"; *") -> 322
D20: сокращение | E20: =COUNTIF('Справочник слов'!C2:C1000,D20)+COUNTIF('Справочник слов'!C2:C1000,D20&", *")+COUNTIF('Справочник слов'!C2:C1000,"*, "&D20)+COUNTIF('Справочник слов'!C2:C1000,"*, "&D20&", *") -> 2 | G20: Путешествия | H20: =COUNTIF('Справочник слов'!E2:E1000,G20)+COUNTIF('Справочник слов'!E2:E1000,G20&"; *")+COUNTIF('Справочник слов'!E2:E1000,"*; "&G20)+COUNTIF('Справочник слов'!E2:E1000,"*; "&G20&"; *") -> 291
D21: союз | E21: =COUNTIF('Справочник слов'!C2:C1000,D21)+COUNTIF('Справочник слов'!C2:C1000,D21&", *")+COUNTIF('Справочник слов'!C2:C1000,"*, "&D21)+COUNTIF('Справочник слов'!C2:C1000,"*, "&D21&", *") -> 56 | G21: Работа | H21: =COUNTIF('Справочник слов'!E2:E1000,G21)+COUNTIF('Справочник слов'!E2:E1000,G21&"; *")+COUNTIF('Справочник слов'!E2:E1000,"*; "&G21)+COUNTIF('Справочник слов'!E2:E1000,"*; "&G21&"; *") -> 367
D22: суффикс | E22: =COUNTIF('Справочник слов'!C2:C1000,D22)+COUNTIF('Справочник слов'!C2:C1000,D22&", *")+COUNTIF('Справочник слов'!C2:C1000,"*, "&D22)+COUNTIF('Справочник слов'!C2:C1000,"*, "&D22&", *") -> 1 | G22: Тело и здоровье | H22: =COUNTIF('Справочник слов'!E2:E1000,G22)+COUNTIF('Справочник слов'!E2:E1000,G22&"; *")+COUNTIF('Справочник слов'!E2:E1000,"*; "&G22)+COUNTIF('Справочник слов'!E2:E1000,"*; "&G22&"; *") -> 430
D23: существительное | E23: =COUNTIF('Справочник слов'!C2:C1000,D23)+COUNTIF('Справочник слов'!C2:C1000,D23&", *")+COUNTIF('Справочник слов'!C2:C1000,"*, "&D23)+COUNTIF('Справочник слов'!C2:C1000,"*, "&D23&", *") -> 6076 | G23: Технологии | H23: =COUNTIF('Справочник слов'!E2:E1000,G23)+COUNTIF('Справочник слов'!E2:E1000,G23&"; *")+COUNTIF('Справочник слов'!E2:E1000,"*; "&G23)+COUNTIF('Справочник слов'!E2:E1000,"*; "&G23&"; *") -> 271
D24: фраза | E24: =COUNTIF('Справочник слов'!C2:C1000,D24)+COUNTIF('Справочник слов'!C2:C1000,D24&", *")+COUNTIF('Справочник слов'!C2:C1000,"*, "&D24)+COUNTIF('Справочник слов'!C2:C1000,"*, "&D24&", *") -> 57 | G24: Характер человека | H24: =COUNTIF('Справочник слов'!E2:E1000,G24)+COUNTIF('Справочник слов'!E2:E1000,G24&"; *")+COUNTIF('Справочник слов'!E2:E1000,"*; "&G24)+COUNTIF('Справочник слов'!E2:E1000,"*; "&G24&"; *") -> 972
D25: фразовый глагол | E25: =COUNTIF('Справочник слов'!C2:C1000,D25)+COUNTIF('Справочник слов'!C2:C1000,D25&", *")+COUNTIF('Справочник слов'!C2:C1000,"*, "&D25)+COUNTIF('Справочник слов'!C2:C1000,"*, "&D25&", *") -> 1074
D26: числительное | E26: =COUNTIF('Справочник слов'!C2:C1000,D26)+COUNTIF('Справочник слов'!C2:C1000,D26&", *")+COUNTIF('Справочник слов'!C2:C1000,"*, "&D26)+COUNTIF('Справочник слов'!C2:C1000,"*, "&D26&", *") -> 43
G30: Записи с несколькими темами учитываются в каждой категории.
D32: Записи с несколькими типами учитываются в каждой категории.
